list_all_files_recursively/LICENSE
list_all_files_recursively/README.MD
list_all_files_recursively/__init__.py
list_all_files_recursively/requirements.txt
list_all_files_recursively/thirdparty.json
list_all_files_recursively-0.12.dist-info/LICENSE.rst
list_all_files_recursively-0.12.dist-info/METADATA
list_all_files_recursively-0.12.dist-info/WHEEL
list_all_files_recursively-0.12.dist-info/top_level.txt
list_all_files_recursively-0.12.dist-info/RECORD
